_boom.cpython-311-x86_64-linux-gnu.so
BayesBoom-0.1.34.dist-info/RECORD
BayesBoom-0.1.34.dist-info/top_level.txt
BayesBoom-0.1.34.dist-info/WHEEL
BayesBoom-0.1.34.dist-info/METADATA
BayesBoom/R/empirical_distribution.py
BayesBoom/R/bayes.py
BayesBoom/R/summary.py
BayesBoom/R/pandas_json.py
BayesBoom/R/frequency_distribution.py
BayesBoom/R/test_utilities.py
BayesBoom/R/plots.py
BayesBoom/R/density.py
BayesBoom/R/probability.py
BayesBoom/R/encoding.py
BayesBoom/R/mcmc.py
BayesBoom/R/stats.py
BayesBoom/R/autoclean.py
BayesBoom/R/__init__.py
BayesBoom/R/base.py
BayesBoom/R/graphics_device.py
BayesBoom/R/ls.py
BayesBoom/R/utils.py
BayesBoom/R/lm.py
BayesBoom/R/boom_py_utils.py
BayesBoom/R/cbind.py
BayesBoom/R/pretty.py
BayesBoom/R/assign_classes.py
BayesBoom/spikeslab/spikeslab.py
BayesBoom/spikeslab/mlogit_test.py
BayesBoom/spikeslab/spikeslab_test.py
BayesBoom/spikeslab/__init__.py
BayesBoom/spikeslab/mlogit_spike.py
BayesBoom/spikeslab/priors.py
BayesBoom/dynreg/test_dynreg.py
BayesBoom/dynreg/dynreg.py
BayesBoom/dynreg/__init__.py
BayesBoom/bayesreg/mean_function.py
BayesBoom/bayesreg/gaussian_process.py
BayesBoom/bayesreg/kernels.py
BayesBoom/bayesreg/hierarchical_gaussian_process.py
BayesBoom/bayesreg/gp_test.py
BayesBoom/bayesreg/__init__.py
BayesBoom/bayesreg/hgp_test.py
BayesBoom/bsts/student_local_linear_trend.py
BayesBoom/bsts/state_models.py
BayesBoom/bsts/test_ar.py
BayesBoom/bsts/airpass.py
BayesBoom/bsts/ar.py
BayesBoom/bsts/holiday.py
BayesBoom/bsts/local_level.py
BayesBoom/bsts/test_utilities.py
BayesBoom/bsts/student.py
BayesBoom/bsts/test_holidays.py
BayesBoom/bsts/data.py
BayesBoom/bsts/poisson.py
BayesBoom/bsts/test_dynamic_regression.py
BayesBoom/bsts/test_seasonal_llt.py
BayesBoom/bsts/test_bsts.py
BayesBoom/bsts/holiday_models.py
BayesBoom/bsts/general_seasonal_llt.py
BayesBoom/bsts/logit.py
BayesBoom/bsts/test_student_llt.py
BayesBoom/bsts/__init__.py
BayesBoom/bsts/dynamic_regression_state_model.py
BayesBoom/bsts/seasonal.py
BayesBoom/bsts/gaussian.py
BayesBoom/bsts/test_state_models.py
