Metadata-Version: 2.1
Name: BayesBoom
Version: 0.1.34
Summary: Tools for Bayesian modeling.
Home-page: https://github.com/steve-the-bayesian/BOOM
Author: Steven L. Scott
Author-email: steve.the.bayesian@gmail.com
Requires-Dist: pybind11>=2.3
